{"Rank":{"4":5,"5":6,"12":13,"21":22,"30":31},"Name":{"4":"Pokemon Red\/Pokemon Blue","5":"Tetris","12":"Pokemon Gold\/Pokemon Silver","21":"Super Mario Land","30":"Pok\u00e9mon Yellow: Special Pikachu Edition"},"Platform":{"4":"GB","5":"GB","12":"GB","21":"GB","30":"GB"},"Year":{"4":1996.0,"5":1989.0,"12":1999.0,"21":1989.0,"30":1998.0},"Genre":{"4":"Role-Playing","5":"Puzzle","12":"Role-Playing","21":"Platform","30":"Role-Playing"},"Publisher":{"4":"Nintendo","5":"Nintendo","12":"Nintendo","21":"Nintendo","30":"Nintendo"},"NA_Sales":{"4":11.27,"5":23.2,"12":9.0,"21":10.83,"30":5.89},"EU_Sales":{"4":8.89,"5":2.26,"12":6.18,"21":2.71,"30":5.04},"JP_Sales":{"4":10.22,"5":4.22,"12":7.2,"21":4.18,"30":3.12},"Other_Sales":{"4":1.0,"5":0.58,"12":0.71,"21":0.42,"30":0.59},"Global_Sales":{"4":31.37,"5":30.26,"12":23.1,"21":18.14,"30":14.64}}